importsearch/__init__.py
importsearch/core.py
importsearch/tree.py
importsearch-0.1.2.dist-info/METADATA
importsearch-0.1.2.dist-info/WHEEL
importsearch-0.1.2.dist-info/licenses/LICENSE
importsearch-0.1.2.dist-info/RECORD
