Metadata-Version: 2.4
Name: importsearch
Version: 0.1.2
Summary: A package to track your imports
Project-URL: Homepage, https://github.com/eto56/ImportSearch
Project-URL: Issues, https://github.com/eto56/ImportSearch/issues
Author: eto56
License-Expression: MIT
License-File: LICENSE
Classifier: Operating System :: OS Independent
Classifier: Programming Language :: Python :: 3
Requires-Python: >=3.8
